ccdjangodeploy/cc.py
ccdjangodeploy/cli.py
ccdjangodeploy/update.py
ccdjangodeploy-1.1.3.dist-info/DESCRIPTION.rst
ccdjangodeploy-1.1.3.dist-info/METADATA
ccdjangodeploy-1.1.3.dist-info/RECORD
ccdjangodeploy-1.1.3.dist-info/WHEEL
ccdjangodeploy-1.1.3.dist-info/entry_points.txt
ccdjangodeploy-1.1.3.dist-info/metadata.json
ccdjangodeploy-1.1.3.dist-info/top_level.txt
